truckeefs/__init__.py
truckeefs/__main__.py
truckeefs/truckeefs.py
truckeefs-0.0.7.dist-info/METADATA
truckeefs-0.0.7.dist-info/WHEEL
truckeefs-0.0.7.dist-info/entry_points.txt
truckeefs-0.0.7.dist-info/top_level.txt
truckeefs-0.0.7.dist-info/RECORD
